{
  "cluster": "Refund",
  "events": [
    {
      "activity": "Issue Reported",
      "timestamp": "2024-06-10T09:15:00Z",
      "contextual_activity": "Issue Reported (Negative)",
      "message": "I received the wrong item in my order and would like to request a refund as soon as possible."
    },
    {
      "activity": "Issue Categorised",
      "timestamp": "2024-06-10T09:17:00Z",
      "contextual_activity": "Issue Categorised (Neutral)",
      "message": "The reported issue has been identified as related to a refund request for an incorrect order."
    },
    {
      "activity": "Agent Assigned",
      "timestamp": "2024-06-10T09:20:00Z",
      "contextual_activity": "Agent Assigned (Neutral)",
      "message": "An agent from the refunds team has been assigned to handle this case and will respond shortly."
    },
    {
      "activity": "Agent Greeting",
      "timestamp": "2024-06-10T09:32:00Z",
      "contextual_activity": "Agent Greeting (Positive)",
      "message": "Hello! I’m sorry to hear you received the wrong item. I’m here to help you with your refund request."
    },
    {
      "activity": "Information Requested",
      "timestamp": "2024-06-10T09:35:00Z",
      "contextual_activity": "Information Requested (Neutral)",
      "message": "Could you please provide a photo of the item received and your order number so we can process the refund quickly?"
    },
    {
      "activity": "Customer Reply",
      "timestamp": "2024-06-10T10:05:00Z",
      "contextual_activity": "Customer Reply (Neutral)",
      "message": "Here is a photo of the item I received instead of the one I ordered. My order number is 123456789."
    },
    {
      "activity": "Solution Proposed",
      "timestamp": "2024-06-10T10:20:00Z",
      "contextual_activity": "Solution Proposed (Positive)",
      "message": "Thank you for the details. We will issue a full refund to your original payment method within 3-5 business days."
    },
    {
      "activity": "Customer Feedback Received",
      "timestamp": "2024-06-10T10:45:00Z",
      "contextual_activity": "Customer Feedback Received (Positive)",
      "message": "Thank you for resolving this so quickly! I appreciate the prompt refund offer."
    },
    {
      "activity": "Issue Resolved",
      "timestamp": "2024-06-10T11:00:00Z",
      "contextual_activity": "Issue Resolved (Positive)",
      "message": "We have processed your refund and sent you confirmation. Please let us know if you need further assistance."
    },
    {
      "activity": "Follow-up Sent",
      "timestamp": "2024-06-17T09:00:00Z",
      "contextual_activity": "Follow-up Sent (Neutral)",
      "message": "Just checking in to confirm that your refund was received and everything is resolved to your satisfaction."
    },
    {
      "activity": "Case Closed",
      "timestamp": "2024-06-17T09:30:00Z",
      "contextual_activity": "Case Closed (Positive)",
      "message": "Since we have not heard back and the refund was processed, we will now close this case. Thank you for contacting us."
    },
    {
      "activity": "Survey Sent",
      "timestamp": "2024-06-17T09:35:00Z",
      "contextual_activity": "Survey Sent (Neutral)",
      "message": "We have sent a short satisfaction survey to help us improve our customer service. Your feedback is appreciated."
    }
  ]
}