{
  "cluster": "Personal Loan",
  "events": [
    {
      "activity": "Application Submitted",
      "timestamp": "2024-01-05T09:15:00Z",
      "contextual_activity": "Application Submitted (Positive)",
      "message": "Applicant submitted the loan form seeking personal loan funds for medical expenses requiring urgent attention."
    },
    {
      "activity": "Application Categorised",
      "timestamp": "2024-01-05T10:00:00Z",
      "contextual_activity": "Application Categorised (Neutral)",
      "message": "The application has been categorised under personal loans given the applicant's stated use for medical bills."
    },
    {
      "activity": "Loan Officer Assigned",
      "timestamp": "2024-01-05T10:30:00Z",
      "contextual_activity": "Loan Officer Assigned (Positive)",
      "message": "Loan officer Emily Turner was assigned to handle the personal loan request and contact the applicant for next steps."
    },
    {
      "activity": "Initial Review",
      "timestamp": "2024-01-06T11:45:00Z",
      "contextual_activity": "Initial Review (Neutral)",
      "message": "Initial review completed focusing on applicant credit history and purpose of loan for covering medical treatment costs."
    },
    {
      "activity": "Documents Requested",
      "timestamp": "2024-01-06T12:00:00Z",
      "contextual_activity": "Documents Requested (Neutral)",
      "message": "Applicant was asked to provide recent medical bills, proof of income, and identification documents for verification."
    },
    {
      "activity": "Documents Submitted",
      "timestamp": "2024-01-08T14:20:00Z",
      "contextual_activity": "Documents Submitted (Positive)",
      "message": "Applicant promptly submitted all requested documentation including medical invoices and recent pay stubs."
    },
    {
      "activity": "Credit Check Completed",
      "timestamp": "2024-01-09T09:00:00Z",
      "contextual_activity": "Credit Check Completed (Neutral)",
      "message": "Credit check finalized showing a good credit score with minor existing debts, overall creditworthiness confirmed."
    },
    {
      "activity": "Risk Assessment Completed",
      "timestamp": "2024-01-09T15:00:00Z",
      "contextual_activity": "Risk Assessment Completed (Positive)",
      "message": "Risk assessment indicates acceptable risk level given applicant’s stable income and emergency medical need."
    },
    {
      "activity": "Offer Presented",
      "timestamp": "2024-01-10T10:00:00Z",
      "contextual_activity": "Offer Presented (Positive)",
      "message": "Loan offer made presenting favorable interest rates and repayment schedule tailored to applicant’s capacity."
    },
    {
      "activity": "Applicant Feedback Received",
      "timestamp": "2024-01-11T08:30:00Z",
      "contextual_activity": "Applicant Feedback Received (Positive)",
      "message": "Applicant confirmed understanding of terms and expressed acceptance of the loan offer conditions."
    },
    {
      "activity": "Application Escalated",
      "timestamp": "2024-01-11T12:00:00Z",
      "contextual_activity": "Application Escalated (Neutral)",
      "message": "Application escalated to senior management for approval given the loan amount exceeded routine thresholds."
    },
    {
      "activity": "Loan Approved",
      "timestamp": "2024-01-12T09:00:00Z",
      "contextual_activity": "Loan Approved (Positive)",
      "message": "Senior management approved the loan application with agreed terms suitable for the applicant’s needs."
    },
    {
      "activity": "Loan Funded",
      "timestamp": "2024-01-12T15:30:00Z",
      "contextual_activity": "Loan Funded (Positive)",
      "message": "Loan amount disbursed successfully to applicant’s bank account to cover the planned medical expenses."
    },
    {
      "activity": "Post-Approval Follow-up",
      "timestamp": "2024-01-20T10:00:00Z",
      "contextual_activity": "Post-Approval Follow-up (Neutral)",
      "message": "Follow-up call confirmed the applicant received funds and is satisfied with the loan process experience."
    },
    {
      "activity": "Application Closed",
      "timestamp": "2024-01-21T09:00:00Z",
      "contextual_activity": "Application Closed (Positive)",
      "message": "Loan application formally closed in system after successful disbursement and completion of all processing steps."
    }
  ]
}