{
  "cluster": "Auto Loan",
  "events": [
    {
      "activity": "Application Submitted",
      "timestamp": "2024-05-01T09:15:00Z",
      "contextual_activity": "Application Submitted (Positive)",
      "message": "Applicant John Smith submitted the auto loan application to finance the purchase of a new sedan."
    },
    {
      "activity": "Application Categorised",
      "timestamp": "2024-05-01T10:00:00Z",
      "contextual_activity": "Application Categorised (Neutral)",
      "message": "Application was reviewed and categorised under Auto Loan based on vehicle financing keywords."
    },
    {
      "activity": "Loan Officer Assigned",
      "timestamp": "2024-05-01T10:30:00Z",
      "contextual_activity": "Loan Officer Assigned (Positive)",
      "message": "Loan officer Karen Lee was assigned to manage this auto loan request for efficient processing."
    },
    {
      "activity": "Initial Review",
      "timestamp": "2024-05-02T14:00:00Z",
      "contextual_activity": "Initial Review (Neutral)",
      "message": "The initial review was conducted to verify applicant information and loan purpose for a car purchase."
    },
    {
      "activity": "Documents Requested",
      "timestamp": "2024-05-02T15:00:00Z",
      "contextual_activity": "Documents Requested (Neutral)",
      "message": "Applicant was asked to submit proof of income, driver license, and vehicle purchase agreement documents."
    },
    {
      "activity": "Documents Submitted",
      "timestamp": "2024-05-04T11:45:00Z",
      "contextual_activity": "Documents Submitted (Positive)",
      "message": "Applicant provided all requested documents including the purchase agreement and proof of income."
    },
    {
      "activity": "Credit Check Completed",
      "timestamp": "2024-05-05T09:00:00Z",
      "contextual_activity": "Credit Check Completed (Neutral)",
      "message": "The credit check report was completed showing a good credit score suitable for auto loan approval."
    },
    {
      "activity": "Risk Assessment Completed",
      "timestamp": "2024-05-05T12:30:00Z",
      "contextual_activity": "Risk Assessment Completed (Positive)",
      "message": "Risk assessment identified low risk due to steady income and strong credit history."
    },
    {
      "activity": "Offer Presented",
      "timestamp": "2024-05-06T10:00:00Z",
      "contextual_activity": "Offer Presented (Positive)",
      "message": "An auto loan offer with competitive interest rates and terms was presented to the applicant."
    },
    {
      "activity": "Applicant Feedback Received",
      "timestamp": "2024-05-07T13:00:00Z",
      "contextual_activity": "Applicant Feedback Received (Positive)",
      "message": "Applicant responded positively to the loan offer and expressed intent to proceed with the terms."
    },
    {
      "activity": "Loan Approved",
      "timestamp": "2024-05-08T09:30:00Z",
      "contextual_activity": "Loan Approved (Positive)",
      "message": "Loan was approved by the credit committee following satisfactory evaluations and applicant feedback."
    },
    {
      "activity": "Loan Funded",
      "timestamp": "2024-05-08T16:45:00Z",
      "contextual_activity": "Loan Funded (Positive)",
      "message": "Loan funds were successfully disbursed to the dealer to complete the car purchase transaction."
    },
    {
      "activity": "Post-Approval Follow-up",
      "timestamp": "2024-05-15T10:00:00Z",
      "contextual_activity": "Post-Approval Follow-up (Neutral)",
      "message": "Follow-up call was conducted to confirm that the applicant received the vehicle and is satisfied."
    },
    {
      "activity": "Application Closed",
      "timestamp": "2024-05-16T09:00:00Z",
      "contextual_activity": "Application Closed (Positive)",
      "message": "The auto loan application case was closed successfully after all procedures were completed."
    }
  ]
}