{
  "cluster": "Personal Loan",
  "events": [
    {
      "activity": "Application Submitted",
      "timestamp": "2024-05-01T08:30:00Z",
      "contextual_activity": "Application Submitted (Positive)",
      "message": "Applicant submitted the personal loan application to cover upcoming medical expenses and related costs."
    },
    {
      "activity": "Application Categorised",
      "timestamp": "2024-05-01T09:00:00Z",
      "contextual_activity": "Application Categorised (Neutral)",
      "message": "Loan application was reviewed and categorized under personal loans as the purpose cited was medical treatment."
    },
    {
      "activity": "Loan Officer Assigned",
      "timestamp": "2024-05-01T10:15:00Z",
      "contextual_activity": "Loan Officer Assigned (Positive)",
      "message": "Assigned a loan officer specialized in personal loans to guide the applicant through the process."
    },
    {
      "activity": "Initial Review",
      "timestamp": "2024-05-02T14:00:00Z",
      "contextual_activity": "Initial Review (Neutral)",
      "message": "Conducted an initial review of the application to ensure completeness and check for preliminary eligibility."
    },
    {
      "activity": "Documents Requested",
      "timestamp": "2024-05-02T15:30:00Z",
      "contextual_activity": "Documents Requested (Neutral)",
      "message": "Requested additional income verification documents and medical bills to support the personal loan application."
    },
    {
      "activity": "Documents Submitted",
      "timestamp": "2024-05-04T11:20:00Z",
      "contextual_activity": "Documents Submitted (Positive)",
      "message": "Applicant submitted all requested medical bills, pay stubs, and identification documents for final review."
    },
    {
      "activity": "Credit Check Completed",
      "timestamp": "2024-05-05T09:45:00Z",
      "contextual_activity": "Credit Check Completed (Neutral)",
      "message": "Performed credit check on the applicant showing a satisfactory credit score with no recent defaults."
    },
    {
      "activity": "Risk Assessment Completed",
      "timestamp": "2024-05-05T13:30:00Z",
      "contextual_activity": "Risk Assessment Completed (Neutral)",
      "message": "Evaluated the risk profile considering the applicant’s income, credit score, and medical expense needs."
    },
    {
      "activity": "Offer Presented",
      "timestamp": "2024-05-06T10:00:00Z",
      "contextual_activity": "Offer Presented (Positive)",
      "message": "The loan offer was presented to the applicant with clear terms and a manageable repayment schedule."
    },
    {
      "activity": "Applicant Feedback Received",
      "timestamp": "2024-05-06T14:45:00Z",
      "contextual_activity": "Applicant Feedback Received (Positive)",
      "message": "Applicant responded positively to the loan offer, expressing satisfaction with the interest rate and terms."
    },
    {
      "activity": "Loan Approved",
      "timestamp": "2024-05-07T09:00:00Z",
      "contextual_activity": "Loan Approved (Positive)",
      "message": "Loan approved by underwriting after confirming all documents and assessments met the bank’s criteria."
    },
    {
      "activity": "Loan Funded",
      "timestamp": "2024-05-08T16:30:00Z",
      "contextual_activity": "Loan Funded (Positive)",
      "message": "Funds disbursed to applicant’s account to cover the medical expenses outlined in the application."
    },
    {
      "activity": "Post-Approval Follow-up",
      "timestamp": "2024-05-15T10:00:00Z",
      "contextual_activity": "Post-Approval Follow-up (Neutral)",
      "message": "Followed up with applicant to ensure loan repayment setup is in place and assess satisfaction with the service."
    },
    {
      "activity": "Application Closed",
      "timestamp": "2024-05-15T12:00:00Z",
      "contextual_activity": "Application Closed (Positive)",
      "message": "Loan application process closed successfully with all documentation completed and funds delivered."
    }
  ]
}