{
  "cluster": "Personal Loan",
  "events": [
    {
      "activity": "Application Submitted",
      "timestamp": "2024-04-01T09:15:00Z",
      "contextual_activity": "Application Submitted (Positive)",
      "message": "Applicant submitted a personal loan application seeking funds to cover outstanding medical expenses and related costs."
    },
    {
      "activity": "Application Categorised",
      "timestamp": "2024-04-01T11:00:00Z",
      "contextual_activity": "Application Categorised (Neutral)",
      "message": "Loan application categorized under personal loan due to keywords indicating medical and personal finance needs."
    },
    {
      "activity": "Loan Officer Assigned",
      "timestamp": "2024-04-01T13:45:00Z",
      "contextual_activity": "Loan Officer Assigned (Positive)",
      "message": "Loan officer John Smith assigned to the case to assist with applicant queries and guide through the process."
    },
    {
      "activity": "Initial Review",
      "timestamp": "2024-04-02T08:30:00Z",
      "contextual_activity": "Initial Review (Neutral)",
      "message": "Initial review completed highlighting the applicant’s stable income but pointing out the significant existing debts."
    },
    {
      "activity": "Documents Requested",
      "timestamp": "2024-04-02T09:15:00Z",
      "contextual_activity": "Documents Requested (Neutral)",
      "message": "Requested supporting documents including recent pay slips, medical bills, and proof of identity to proceed with verification."
    },
    {
      "activity": "Documents Submitted",
      "timestamp": "2024-04-04T15:00:00Z",
      "contextual_activity": "Documents Submitted (Positive)",
      "message": "Applicant submitted all requested documents promptly enabling swift continuation of loan processing."
    },
    {
      "activity": "Credit Check Completed",
      "timestamp": "2024-04-05T10:25:00Z",
      "contextual_activity": "Credit Check Completed (Neutral)",
      "message": "Credit check shows a moderately good rating; however, some previous late payments noted on credit report history."
    },
    {
      "activity": "Risk Assessment Completed",
      "timestamp": "2024-04-05T14:45:00Z",
      "contextual_activity": "Risk Assessment Completed (Neutral)",
      "message": "Risk assessment concluded moderate risk due to high outstanding debts balanced by steady employment income."
    },
    {
      "activity": "Offer Presented",
      "timestamp": "2024-04-06T09:00:00Z",
      "contextual_activity": "Offer Presented (Positive)",
      "message": "Loan offer presented to applicant including terms and interest rate tailored to the personal financial circumstances."
    },
    {
      "activity": "Applicant Feedback Received",
      "timestamp": "2024-04-07T11:30:00Z",
      "contextual_activity": "Applicant Feedback Received (Neutral)",
      "message": "Applicant requested minor revisions to repayment schedule citing upcoming wedding expenses within the year."
    },
    {
      "activity": "Application Escalated",
      "timestamp": "2024-04-07T14:10:00Z",
      "contextual_activity": "Application Escalated (Neutral)",
      "message": "Application escalated to senior loan committee due to requested repayment modifications and additional risk considerations."
    },
    {
      "activity": "Loan Approved",
      "timestamp": "2024-04-08T10:30:00Z",
      "contextual_activity": "Loan Approved (Positive)",
      "message": "Loan approved by committee with adjusted terms incorporating applicant’s feedback on repayment flexibility."
    },
    {
      "activity": "Loan Funded",
      "timestamp": "2024-04-08T16:00:00Z",
      "contextual_activity": "Loan Funded (Positive)",
      "message": "Funds successfully disbursed to applicant’s account enabling immediate use for medical and personal financial needs."
    },
    {
      "activity": "Post-Approval Follow-up",
      "timestamp": "2024-04-15T10:00:00Z",
      "contextual_activity": "Post-Approval Follow-up (Positive)",
      "message": "Follow-up call made confirming applicant satisfaction and providing reminders about upcoming repayment schedule."
    },
    {
      "activity": "Application Closed",
      "timestamp": "2024-04-20T12:00:00Z",
      "contextual_activity": "Application Closed (Positive)",
      "message": "All required steps completed and loan process formally closed with positive client feedback on service experience."
    }
  ]
}