{
  "cluster": "Personal Loan",
  "events": [
    {
      "activity": "Application Submitted",
      "timestamp": "2024-04-01T09:15:00Z",
      "contextual_activity": "Application Submitted (Positive)",
      "message": "Applicant has submitted a personal loan application to cover medical expenses incurred recently."
    },
    {
      "activity": "Application Categorised",
      "timestamp": "2024-04-01T10:00:00Z",
      "contextual_activity": "Application Categorised (Neutral)",
      "message": "The loan application has been classified under personal loans after review of the applicant's stated purpose."
    },
    {
      "activity": "Loan Officer Assigned",
      "timestamp": "2024-04-01T11:30:00Z",
      "contextual_activity": "Loan Officer Assigned (Positive)",
      "message": "A loan officer specialized in personal loans has been assigned to assist the applicant through the process."
    },
    {
      "activity": "Initial Review",
      "timestamp": "2024-04-02T14:00:00Z",
      "contextual_activity": "Initial Review (Neutral)",
      "message": "The initial review of submitted documents and application form has been completed without identifying issues."
    },
    {
      "activity": "Documents Requested",
      "timestamp": "2024-04-02T15:30:00Z",
      "contextual_activity": "Documents Requested (Neutral)",
      "message": "Additional financial statements and medical bills have been requested to verify the loan purpose and applicant’s ability to repay."
    },
    {
      "activity": "Documents Submitted",
      "timestamp": "2024-04-04T10:45:00Z",
      "contextual_activity": "Documents Submitted (Positive)",
      "message": "Applicant has submitted all requested documents including detailed medical receipts and proof of income."
    },
    {
      "activity": "Credit Check Completed",
      "timestamp": "2024-04-05T12:00:00Z",
      "contextual_activity": "Credit Check Completed (Neutral)",
      "message": "Credit history review has been completed showing a stable credit score with minor past credit usage."
    },
    {
      "activity": "Risk Assessment Completed",
      "timestamp": "2024-04-05T15:30:00Z",
      "contextual_activity": "Risk Assessment Completed (Neutral)",
      "message": "Risk assessment indicates a moderate risk profile considering applicant’s income and outstanding obligations."
    },
    {
      "activity": "Offer Presented",
      "timestamp": "2024-04-06T09:00:00Z",
      "contextual_activity": "Offer Presented (Positive)",
      "message": "A personal loan offer detailing terms, interest rates, and repayment schedule has been presented to the applicant."
    },
    {
      "activity": "Applicant Feedback Received",
      "timestamp": "2024-04-06T16:45:00Z",
      "contextual_activity": "Applicant Feedback Received (Positive)",
      "message": "The applicant expressed satisfaction with the offer and has requested clarification on early repayment penalties."
    },
    {
      "activity": "Application Escalated",
      "timestamp": "2024-04-07T11:30:00Z",
      "contextual_activity": "Application Escalated (Neutral)",
      "message": "The application has been escalated to senior management for approval due to the loan amount exceeding standard limits."
    },
    {
      "activity": "Loan Approved",
      "timestamp": "2024-04-08T10:00:00Z",
      "contextual_activity": "Loan Approved (Positive)",
      "message": "Senior management approved the personal loan application after reviewing all documents and risk assessments."
    },
    {
      "activity": "Loan Funded",
      "timestamp": "2024-04-09T08:30:00Z",
      "contextual_activity": "Loan Funded (Positive)",
      "message": "Loan funds have been successfully disbursed to the applicant’s bank account as per the agreed schedule."
    },
    {
      "activity": "Post-Approval Follow-up",
      "timestamp": "2024-04-15T09:00:00Z",
      "contextual_activity": "Post-Approval Follow-up (Positive)",
      "message": "A follow-up call was made to ensure the applicant has received the funds and to answer any further questions."
    },
    {
      "activity": "Application Closed",
      "timestamp": "2024-04-15T17:00:00Z",
      "contextual_activity": "Application Closed (Positive)",
      "message": "The personal loan application case has been officially closed after successful loan disbursement and follow-up."
    }
  ]
}