{
  "cluster": "Auto Accident",
  "events": [
    {
      "activity": "Claim Filed",
      "timestamp": "2024-05-10T08:30:00Z",
      "contextual_activity": "Claim Filed (Neutral)",
      "message": "Customer reported a collision involving their vehicle on the highway around 7 AM, initiating the claim process."
    },
    {
      "activity": "Claim Categorised",
      "timestamp": "2024-05-10T10:00:00Z",
      "contextual_activity": "Claim Categorised (Neutral)",
      "message": "The claim was reviewed and categorised under Auto Accident due to car collision on public road."
    },
    {
      "activity": "Agent Assigned",
      "timestamp": "2024-05-10T10:30:00Z",
      "contextual_activity": "Agent Assigned (Positive)",
      "message": "A dedicated claims agent was assigned promptly to handle the accident case and coordinate with the customer."
    },
    {
      "activity": "Claim Acknowledged",
      "timestamp": "2024-05-10T11:00:00Z",
      "contextual_activity": "Claim Acknowledged (Neutral)",
      "message": "Customer received an official acknowledgment confirming that their auto accident claim has been logged."
    },
    {
      "activity": "Documents Requested",
      "timestamp": "2024-05-11T09:00:00Z",
      "contextual_activity": "Documents Requested (Neutral)",
      "message": "Agent requested official police report, photos of damaged vehicle, and insurance policy documents for investigation."
    },
    {
      "activity": "Documents Submitted",
      "timestamp": "2024-05-12T14:45:00Z",
      "contextual_activity": "Documents Submitted (Positive)",
      "message": "Customer submitted all required documentation including photos, police report, and repair estimates promptly."
    },
    {
      "activity": "Investigation Started",
      "timestamp": "2024-05-13T08:00:00Z",
      "contextual_activity": "Investigation Started (Neutral)",
      "message": "The investigation team began evaluating the accident circumstances and examining submitted evidence."
    },
    {
      "activity": "Investigation Completed",
      "timestamp": "2024-05-15T16:30:00Z",
      "contextual_activity": "Investigation Completed (Positive)",
      "message": "Investigation concluded confirming liability and extent of damage consistent with the customer's report."
    },
    {
      "activity": "Settlement Proposed",
      "timestamp": "2024-05-16T12:00:00Z",
      "contextual_activity": "Settlement Proposed (Neutral)",
      "message": "A settlement offer was proposed to cover the repair costs and associated expenses related to the car accident."
    },
    {
      "activity": "Customer Feedback Received",
      "timestamp": "2024-05-17T09:15:00Z",
      "contextual_activity": "Customer Feedback Received (Positive)",
      "message": "Customer provided positive feedback expressing satisfaction with the prompt response and proposed settlement."
    },
    {
      "activity": "Claim Approved",
      "timestamp": "2024-05-18T10:30:00Z",
      "contextual_activity": "Claim Approved (Positive)",
      "message": "The claim approval was finalized following customer acceptance of the settlement proposal."
    },
    {
      "activity": "Payment Issued",
      "timestamp": "2024-05-19T15:00:00Z",
      "contextual_activity": "Payment Issued (Positive)",
      "message": "Payment for the approved settlement was successfully processed and transferred to the customer’s bank account."
    },
    {
      "activity": "Claim Closed",
      "timestamp": "2024-05-20T11:00:00Z",
      "contextual_activity": "Claim Closed (Positive)",
      "message": "The insurance claim was officially closed after confirmation of payment receipt and customer satisfaction."
    },
    {
      "activity": "Claim Archived",
      "timestamp": "2024-05-21T09:00:00Z",
      "contextual_activity": "Claim Archived (Neutral)",
      "message": "All documentation and records related to the auto accident claim have been securely archived for future reference."
    }
  ]
}