{
  "cluster": "Auto Accident",
  "events": [
    {
      "activity": "Claim Filed",
      "timestamp": "2024-05-01T09:15:00Z",
      "contextual_activity": "Claim Filed (Neutral)",
      "message": "Customer submitted initial claim reporting a car collision that occurred on April 28th downtown during rush hour."
    },
    {
      "activity": "Claim Categorised",
      "timestamp": "2024-05-01T10:00:00Z",
      "contextual_activity": "Claim Categorised (Neutral)",
      "message": "The claim was categorized under Auto Accident after reviewing the description and keywords related to vehicle damage."
    },
    {
      "activity": "Agent Assigned",
      "timestamp": "2024-05-01T11:00:00Z",
      "contextual_activity": "Agent Assigned (Positive)",
      "message": "An agent specializing in collision claims was assigned promptly to ensure quick handling and customer support."
    },
    {
      "activity": "Claim Acknowledged",
      "timestamp": "2024-05-01T11:30:00Z",
      "contextual_activity": "Claim Acknowledged (Positive)",
      "message": "Customer received official acknowledgment of the claim filing with an estimated timeline for investigation."
    },
    {
      "activity": "Documents Requested",
      "timestamp": "2024-05-02T08:00:00Z",
      "contextual_activity": "Documents Requested (Neutral)",
      "message": "Request sent to customer to provide accident photos, police report, and vehicle repair estimates for further processing."
    },
    {
      "activity": "Documents Submitted",
      "timestamp": "2024-05-03T14:45:00Z",
      "contextual_activity": "Documents Submitted (Positive)",
      "message": "The customer submitted all required documents including police report and mechanic’s repair quote within the deadline."
    },
    {
      "activity": "Investigation Started",
      "timestamp": "2024-05-04T09:00:00Z",
      "contextual_activity": "Investigation Started (Neutral)",
      "message": "Assigned investigator began assessment of the collision claim, reviewing damages and cross-checking submitted evidence."
    },
    {
      "activity": "Investigation Completed",
      "timestamp": "2024-05-08T17:30:00Z",
      "contextual_activity": "Investigation Completed (Positive)",
      "message": "Investigation concluded with confirmation that the claim meets coverage criteria and extent of damage was validated."
    },
    {
      "activity": "Settlement Proposed",
      "timestamp": "2024-05-09T10:00:00Z",
      "contextual_activity": "Settlement Proposed (Positive)",
      "message": "A settlement offer was proposed to the customer covering repair costs and rental car reimbursement for five days."
    },
    {
      "activity": "Customer Feedback Received",
      "timestamp": "2024-05-10T15:00:00Z",
      "contextual_activity": "Customer Feedback Received (Positive)",
      "message": "Customer provided positive feedback on the responsiveness and clarity of the settlement proposal offered."
    },
    {
      "activity": "Claim Approved",
      "timestamp": "2024-05-11T09:00:00Z",
      "contextual_activity": "Claim Approved (Positive)",
      "message": "The claim was officially approved following customer acceptance of the settlement terms and conditions."
    },
    {
      "activity": "Payment Issued",
      "timestamp": "2024-05-12T13:30:00Z",
      "contextual_activity": "Payment Issued (Positive)",
      "message": "Payment for the approved settlement was issued to the customer’s account to cover repair expenses immediately."
    },
    {
      "activity": "Claim Closed",
      "timestamp": "2024-05-15T10:00:00Z",
      "contextual_activity": "Claim Closed (Positive)",
      "message": "The claim was formally closed after confirming that the customer received payment and vehicle repair was completed."
    },
    {
      "activity": "Claim Archived",
      "timestamp": "2024-05-20T12:00:00Z",
      "contextual_activity": "Claim Archived (Neutral)",
      "message": "All claim-related documents and correspondence were archived securely for future reference and auditing purposes."
    }
  ]
}